{
   "Safety Box": null,
   "Months": {
      "2026-3": {
         "Income": {
            "total": 1200.0,
            "Salary": 1000.0,
            "Allowance": 200.0,
            "Part-time job": 0,
            "Full-time job": 0,
            "Other": 0
         },
         "Saving": {
            "total": 511.0,
            "Emergency": 100.0,
            "Goal": 411.0,
            "General": 0,
            "Other": 0
         },
         "Expense": {
            "total": 70.0,
            "Food": 50.0,
            "Transport": 20.0,
            "Entertainment": 0,
            "Education": 0,
            "Other": 0
         }
      },
      "2026-4": {
         "Income": {
            "total": 1200.0,
            "Salary": 1000.0,
            "Allowance": 200.0,
            "Part-time job": 0,
            "Full-time job": 0,
            "Other": 0
         },
         "Saving": {
            "total": 1300.0,
            "Emergency": 100.0,
            "Goal": 1200.0,
            "General": 0,
            "Other": 0
         },
         "Expense": {
            "total": 70.0,
            "Food": 50.0,
            "Transport": 20.0,
            "Entertainment": 0,
            "Education": 0,
            "Other": 0
         }
      }
   }
}